ergou/__init__.py
ergou/ergou.py
YzyNbbbbbb-0.1.2.dist-info/LICENSE
YzyNbbbbbb-0.1.2.dist-info/METADATA
YzyNbbbbbb-0.1.2.dist-info/WHEEL
YzyNbbbbbb-0.1.2.dist-info/top_level.txt
YzyNbbbbbb-0.1.2.dist-info/RECORD
