Metadata-Version: 2.1
Name: YzyNbbbbbb
Version: 0.1.2
Summary: A simple package with my custom functions
Author: nigulasi_ergou
Author-email: ergou@email.com
License: UNKNOWN
Platform: UNKNOWN
Classifier: Programming Language :: Python :: 3
Classifier: License :: OSI Approved :: MIT License
Classifier: Operating System :: OS Independent
Requires-Python: >=3.6
License-File: LICENSE
